pythonicspring/__init__.py
pythonicspring/configuration/IAbcConfig.py
pythonicspring/configuration/ISpringConfig.py
pythonicspring/configuration/__init__.py
pythonicspring/configuration/bean_config/IBeanConfig.py
pythonicspring/configuration/bean_config/__init__.py
pythonicspring/core/BeanFactory.py
pythonicspring/core/BeanProxy.py
pythonicspring/core/__init__.py
pythonicspring/utils/GlobalInjector.py
pythonicspring/utils/GlobalScanner.py
pythonicspring/utils/TreeUtil.py
pythonicspring/utils/__init__.py
test/TestApp.py
test/TestClassAutowired.py
test/TestIssue6.py
test/__init__.py
test/resources/__init__.py
test/src/ClassA.py
test/src/ClassB.py
test/src/ClassC.py
test/src/__init__.py
pythonic_spring-0.0.1.5.dist-info/LICENSE
pythonic_spring-0.0.1.5.dist-info/METADATA
pythonic_spring-0.0.1.5.dist-info/WHEEL
pythonic_spring-0.0.1.5.dist-info/top_level.txt
pythonic_spring-0.0.1.5.dist-info/RECORD
