Metadata-Version: 2.1
Name: pythonic-spring
Version: 0.0.1.5
Summary: A python-made framework which is like Spring in Java.
Author: Tianhao Zhang
Author-email: genji9071@gmail.com
License: MIT
Project-URL: Source, https://github.com/genji9071/pythonic-spring/
Project-URL: Tracker, https://github.com/genji9071/pythonic-spring/issues
Keywords: spring pythonic
Requires-Python: >=3.7
License-File: LICENSE
Requires-Dist: fastapi (~=0.108.0)
Requires-Dist: setuptools (~=65.5.1)
Requires-Dist: pydantic (~=2.5.3)
